pyslides/__init__.py
pyslides/__main__.py
python_slides-0.0.1.dist-info/METADATA
python_slides-0.0.1.dist-info/WHEEL
python_slides-0.0.1.dist-info/entry_points.txt
python_slides-0.0.1.dist-info/top_level.txt
python_slides-0.0.1.dist-info/RECORD
