Metadata-Version: 2.1
Name: python-slides
Version: 0.0.1
Summary: A Python package for slideshows.
Home-page: https://gitlab.com/BCLegon/pyslides
Author: B.C. Legon
Author-email: pypi@legon.it
License: UNKNOWN
Platform: UNKNOWN
Requires-Dist: Pillow
Requires-Dist: PyPDF2
Requires-Dist: pdf2image
